{
  "id": "adriatic-bank-ad-podgorica-me",
  "type": [
    "account"
  ],
  "bankType": [
    "retail"
  ],
  "name": "ADRIATIC BANK AD PODGORICA",
  "legalName": "ADRIATIC BANK AD PODGORICA",
  "verified": false,
  "status": "live",
  "icon": "https://icons.duckduckgo.com/ip3/www.adriatic-bank-ad-podgorica.com.ico",
  "websiteUrl": null,
  "countryHQ": "ME",
  "countries": [
    "ME"
  ],
  "webApplication": true,
  "mobileApps": [],
  "compliance": [],
  "developerPortalUrl": null,
  "apiStandards": [],
  "apiProducts": [],
  "apiAggregators": [],
  "ownership": [],
  "stateOwned": false,
  "stockSymbol": null,
  "bic": "AZMNMEPG"
}
