{
  "id": "air-canada-pension-master-trust-fund",
  "type": [
    "account"
  ],
  "bankType": [
    "retail"
  ],
  "name": "AIR Canada Pension Master Trust Fund",
  "legalName": "AIR CANADA PENSION MASTER TRUST FUND",
  "verified": false,
  "status": "live",
  "icon": null,
  "websiteUrl": null,
  "countryHQ": "CA",
  "countries": [
    "CA"
  ],
  "webApplication": true,
  "mobileApps": [],
  "compliance": [],
  "developerPortalUrl": null,
  "apiStandards": [],
  "apiProducts": [],
  "apiAggregators": [],
  "ownership": [],
  "stateOwned": false,
  "stockSymbol": null,
  "bic": "ACMTCAMMXXX"
}
