{
  "id": "alliance-plan-retirement-plan-information-line",
  "type": [
    "account"
  ],
  "bankType": [
    "retail"
  ],
  "name": "Alliance Plan - Retirement Plan Information Line",
  "legalName": "Alliance Plan - Retirement Plan Information Line",
  "verified": false,
  "status": "live",
  "icon": "https://icons.duckduckgo.com/ip3/www.alliance-plan-retirement-plan-information-line.com.ico",
  "websiteUrl": "https://alliance-plan.com/",
  "countryHQ": "US",
  "countries": [
    "US"
  ],
  "webApplication": true,
  "mobileApps": [],
  "compliance": [],
  "developerPortalUrl": null,
  "apiStandards": [],
  "apiProducts": [],
  "apiAggregators": [
    "plaid"
  ],
  "ownership": [],
  "stateOwned": false,
  "stockSymbol": null
}
