{
  "id": "almirall-sa",
  "type": [
    "account"
  ],
  "bankType": [
    "retail"
  ],
  "name": "ALMIRALL, S.A.",
  "legalName": "ALMIRALL, S.A.",
  "bic": "PFPFESBBXXX",
  "verified": false,
  "status": "live",
  "icon": "https://icons.duckduckgo.com/ip3/www.almirallsa.com.ico",
  "websiteUrl": null,
  "countryHQ": "ES",
  "countries": [
    "ES"
  ],
  "webApplication": true,
  "mobileApps": [],
  "compliance": [],
  "developerPortalUrl": null,
  "apiStandards": [],
  "apiProducts": [],
  "apiAggregators": [],
  "ownership": [],
  "stateOwned": false,
  "stockSymbol": null
}
