{
  "id": "ameriabank-formerly-armimpexbank",
  "type": [
    "account"
  ],
  "bankType": [
    "retail"
  ],
  "name": "Ameriabank (formerly Armimpexbank)",
  "legalName": "AMERIABANK (FORMERLY ARMIMPEXBANK)",
  "bic": "ARMIAM22XXX",
  "verified": false,
  "status": "live",
  "icon": null,
  "websiteUrl": null,
  "countryHQ": "AM",
  "countries": [
    "AM"
  ],
  "webApplication": true,
  "mobileApps": [],
  "compliance": [],
  "developerPortalUrl": null,
  "apiStandards": [],
  "apiProducts": [],
  "apiAggregators": [],
  "ownership": [],
  "stateOwned": false,
  "stockSymbol": null
}
