{
  "id": "banca-di-credito-cooperativo-di-castagneto-carducci-soc-coop-per-azioni",
  "type": [
    "account"
  ],
  "bankType": [
    "retail"
  ],
  "name": "Banca Di Credito Cooperativo Di Castagneto Carducci Soc. Coop. Per Azioni",
  "legalName": "Banca Di Credito Cooperativo Di Castagneto Carducci Soc. Coop. Per Azioni",
  "verified": false,
  "status": "live",
  "icon": "https://icons.duckduckgo.com/ip3/www.banca-di-credito-cooperativo-di-castagneto-carducci-soc-coop-per-azioni.com.ico",
  "websiteUrl": null,
  "countryHQ": "IT",
  "countries": [
    "IT"
  ],
  "webApplication": true,
  "mobileApps": [],
  "compliance": [],
  "developerPortalUrl": null,
  "apiStandards": [],
  "apiProducts": [],
  "apiAggregators": [
    "gocardless"
  ],
  "ownership": [],
  "stateOwned": false,
  "stockSymbol": null,
  "bic": "BCCDIT3C"
}
