{
  "id": "banco-nacional-de-las-exportaciones-bandex-do",
  "type": [
    "account"
  ],
  "bankType": [
    "retail"
  ],
  "name": "BANCO NACIONAL DE LAS EXPORTACIONES (BANDEX)",
  "legalName": "BANCO NACIONAL DE LAS EXPORTACIONES (BANDEX)",
  "verified": false,
  "status": "live",
  "icon": "https://icons.duckduckgo.com/ip3/www.banco-nacional-de-las-exportaciones-bandex.com.ico",
  "websiteUrl": null,
  "countryHQ": "DO",
  "countries": [
    "DO"
  ],
  "webApplication": true,
  "mobileApps": [],
  "compliance": [],
  "developerPortalUrl": null,
  "apiStandards": [],
  "apiProducts": [],
  "apiAggregators": [],
  "ownership": [],
  "stateOwned": false,
  "stockSymbol": null,
  "bic": "BNVPDOS1"
}
