{
  "id": "banco-do-brasil-sa-es",
  "type": [
    "account"
  ],
  "bankType": [
    "retail"
  ],
  "name": "BANCO DO BRASIL SA",
  "legalName": "BANCO DO BRASIL SA",
  "bic": "BRASESB1XXX",
  "verified": false,
  "status": "live",
  "icon": "https://icons.duckduckgo.com/ip3/www.bancodobrasilsaes.com.ico",
  "websiteUrl": null,
  "countryHQ": "ES",
  "countries": [
    "ES"
  ],
  "webApplication": true,
  "mobileApps": [],
  "compliance": [],
  "developerPortalUrl": null,
  "apiStandards": [],
  "apiProducts": [],
  "apiAggregators": [],
  "ownership": [],
  "stateOwned": false,
  "stockSymbol": null
}
