{
  "id": "bank-insinger-de-beaufort-nv-italia",
  "type": [
    "account"
  ],
  "bankType": [
    "retail"
  ],
  "name": "BANK INSINGER DE BEAUFORT N.V. (ITALIA)",
  "legalName": "BANK INSINGER DE BEAUFORT N.V. (ITALIA)",
  "verified": false,
  "status": "live",
  "icon": "https://icons.duckduckgo.com/ip3/www.bankinsingerdebeaufortnvitalia.com.ico",
  "websiteUrl": null,
  "countryHQ": "IT",
  "countries": [
    "IT"
  ],
  "webApplication": true,
  "mobileApps": [],
  "compliance": [],
  "developerPortalUrl": null,
  "apiStandards": [],
  "apiProducts": [],
  "apiAggregators": [],
  "ownership": [],
  "stateOwned": false,
  "stockSymbol": null,
  "bic": "INSIITR1XXX"
}
