{
  "id": "bank-negara-indonesia-persero-pt-tokyo-branch",
  "type": [
    "account"
  ],
  "bankType": [
    "retail"
  ],
  "name": "BANK NEGARA INDONESIA (PERSERO), PT., TOKYO BRANCH",
  "legalName": "BANK NEGARA INDONESIA (PERSERO), PT., TOKYO BRANCH",
  "bic": "BNINJPJTXXX",
  "verified": false,
  "status": "live",
  "icon": "https://icons.duckduckgo.com/ip3/www.banknegaraindonesiaperseropttokyobranch.com.ico",
  "websiteUrl": null,
  "countryHQ": "JP",
  "countries": [
    "JP"
  ],
  "webApplication": true,
  "mobileApps": [],
  "compliance": [],
  "developerPortalUrl": null,
  "apiStandards": [],
  "apiProducts": [],
  "apiAggregators": [],
  "ownership": [],
  "stateOwned": false,
  "stockSymbol": null
}
