{
  "id": "bankers-trust-company-of-california",
  "type": [
    "account"
  ],
  "bankType": [
    "retail"
  ],
  "name": "BANKERS TRUST COMPANY OF CALIFORNIA",
  "legalName": "BANKERS TRUST COMPANY OF CALIFORNIA",
  "bic": "TRCCUS61XXX",
  "verified": false,
  "status": "live",
  "icon": "https://icons.duckduckgo.com/ip3/www.bankerstrustcompanyofcalifornia.com.ico",
  "websiteUrl": null,
  "countryHQ": "US",
  "countries": [
    "US"
  ],
  "webApplication": true,
  "mobileApps": [],
  "compliance": [],
  "developerPortalUrl": null,
  "apiStandards": [],
  "apiProducts": [],
  "apiAggregators": [],
  "ownership": [],
  "stateOwned": false,
  "stockSymbol": null
}
