{
  "id": "bank-of-north-dakota",
  "type": [
    "account"
  ],
  "bankType": [
    "retail"
  ],
  "name": "Bank of North Dakota",
  "legalName": "Bank of North Dakota",
  "verified": false,
  "status": "live",
  "icon": "https://icons.duckduckgo.com/ip3/www.bank-of-north-dakota.com.ico",
  "websiteUrl": "https://bnd.nd.gov/",
  "countryHQ": "US",
  "countries": [
    "US"
  ],
  "webApplication": true,
  "mobileApps": [],
  "compliance": [],
  "developerPortalUrl": null,
  "apiStandards": [],
  "apiProducts": [],
  "apiAggregators": [
    "plaid"
  ],
  "ownership": [],
  "stateOwned": false,
  "stockSymbol": null
}
