{
  "id": "banque-pour-invest-prof-liberales",
  "type": [
    "account"
  ],
  "bankType": [
    "retail"
  ],
  "name": "BANQUE POUR INVEST. PROF. LIBERALES",
  "legalName": "BANQUE POUR INVEST. PROF. LIBERALES",
  "bic": "INPLFRP1XXX",
  "verified": false,
  "status": "live",
  "icon": "https://icons.duckduckgo.com/ip3/www.banquepourinvestprofliberales.com.ico",
  "websiteUrl": null,
  "countryHQ": "FR",
  "countries": [
    "FR"
  ],
  "webApplication": true,
  "mobileApps": [],
  "compliance": [],
  "developerPortalUrl": null,
  "apiStandards": [],
  "apiProducts": [],
  "apiAggregators": [],
  "ownership": [],
  "stateOwned": false,
  "stockSymbol": null
}
