{
  "id": "banque-europeenne-du-credit-mutuel",
  "type": [
    "account"
  ],
  "bankType": [
    "retail"
  ],
  "name": "BANQUE EUROPEENNE DU CREDIT MUTUEL",
  "legalName": "BANQUE EUROPEENNE DU CREDIT MUTUEL",
  "bic": "CMCIDEF1XXX",
  "verified": false,
  "status": "live",
  "icon": "https://icons.duckduckgo.com/ip3/www.banqueeuropeenneducreditmutuel.com.ico",
  "websiteUrl": null,
  "countryHQ": "DE",
  "countries": [
    "DE"
  ],
  "webApplication": true,
  "mobileApps": [],
  "compliance": [],
  "developerPortalUrl": null,
  "apiStandards": [],
  "apiProducts": [],
  "apiAggregators": [],
  "ownership": [],
  "stateOwned": false,
  "stockSymbol": null
}
