{
  "id": "batimur-sas",
  "type": [
    "account"
  ],
  "bankType": [
    "retail"
  ],
  "name": "BATIMUR SAS",
  "legalName": "BATIMUR SAS",
  "bic": "BAUIFRP1XXX",
  "verified": false,
  "status": "live",
  "icon": "https://icons.duckduckgo.com/ip3/www.batimursas.com.ico",
  "websiteUrl": null,
  "countryHQ": "FR",
  "countries": [
    "FR"
  ],
  "webApplication": true,
  "mobileApps": [],
  "compliance": [],
  "developerPortalUrl": null,
  "apiStandards": [],
  "apiProducts": [],
  "apiAggregators": [],
  "ownership": [],
  "stateOwned": false,
  "stockSymbol": null
}
