{
  "id": "bolsa-de-valencia",
  "type": [
    "account"
  ],
  "bankType": [
    "retail"
  ],
  "name": "BOLSA DE VALENCIA",
  "legalName": "BOLSA DE VALENCIA",
  "verified": false,
  "status": "live",
  "icon": "https://icons.duckduckgo.com/ip3/www.bolsadevalencia.com.ico",
  "websiteUrl": null,
  "countryHQ": "ES",
  "countries": [
    "ES"
  ],
  "webApplication": true,
  "mobileApps": [],
  "compliance": [],
  "developerPortalUrl": null,
  "apiStandards": [],
  "apiProducts": [],
  "apiAggregators": [],
  "ownership": [],
  "stateOwned": false,
  "stockSymbol": null,
  "bic": "XVALESV1XXX"
}
