{
  "id": "brainerd-savings-and-loan-association-a-federal-association",
  "type": [
    "account"
  ],
  "bankType": [
    "retail"
  ],
  "name": "Brainerd Savings and Loan Association, A Federal Association",
  "legalName": "Brainerd Savings and Loan Association, A Federal Association",
  "verified": false,
  "status": "live",
  "icon": "https://icons.duckduckgo.com/ip3/www.brainerd-savings-and-loan-association-a-federal-association.com.ico",
  "websiteUrl": null,
  "countryHQ": "US",
  "countries": [
    "US"
  ],
  "webApplication": true,
  "mobileApps": [],
  "compliance": [],
  "developerPortalUrl": null,
  "apiStandards": [],
  "apiProducts": [],
  "apiAggregators": [],
  "ownership": [],
  "stateOwned": false,
  "stockSymbol": null
}
