{
  "id": "caisse-damortissement-de-la-dette-sociale-fr",
  "type": [
    "account"
  ],
  "bankType": [
    "retail"
  ],
  "name": "CAISSE D'AMORTISSEMENT DE LA DETTE SOCIALE",
  "legalName": "CAISSE D'AMORTISSEMENT DE LA DETTE SOCIALE",
  "verified": false,
  "status": "live",
  "icon": "https://icons.duckduckgo.com/ip3/www.caisse-damortissement-de-la-dette-sociale.com.ico",
  "websiteUrl": null,
  "countryHQ": "FR",
  "countries": [
    "FR"
  ],
  "webApplication": true,
  "mobileApps": [],
  "compliance": [],
  "developerPortalUrl": null,
  "apiStandards": [],
  "apiProducts": [],
  "apiAggregators": [],
  "ownership": [],
  "stateOwned": false,
  "stockSymbol": null,
  "bic": "CADEFRP1"
}
