{
  "id": "caixa-geral-de-depositos-mc",
  "type": [
    "account"
  ],
  "bankType": [
    "retail"
  ],
  "name": "CAIXA GERAL DE DEPOSITOS",
  "legalName": "CAIXA GERAL DE DEPOSITOS",
  "bic": "CGDIMCM1XXX",
  "verified": false,
  "status": "live",
  "icon": "https://icons.duckduckgo.com/ip3/www.caixageraldedepositosmc.com.ico",
  "websiteUrl": null,
  "countryHQ": "MC",
  "countries": [
    "MC"
  ],
  "webApplication": true,
  "mobileApps": [],
  "compliance": [],
  "developerPortalUrl": null,
  "apiStandards": [],
  "apiProducts": [],
  "apiAggregators": [],
  "ownership": [],
  "stateOwned": false,
  "stockSymbol": null
}
