{
  "id": "caja-rural-asturias",
  "type": [
    "account"
  ],
  "bankType": [
    "retail"
  ],
  "name": "Caja Rural Asturias",
  "legalName": "Caja Rural Asturias",
  "verified": false,
  "status": "live",
  "icon": "https://icons.duckduckgo.com/ip3/www.caja-rural-asturias.com.ico",
  "websiteUrl": null,
  "countryHQ": "ES",
  "countries": [
    "ES"
  ],
  "webApplication": true,
  "mobileApps": [],
  "compliance": [],
  "developerPortalUrl": null,
  "apiStandards": [],
  "apiProducts": [],
  "apiAggregators": [
    "gocardless"
  ],
  "ownership": [],
  "stateOwned": false,
  "stockSymbol": null,
  "bic": "BCOEESMM059"
}
