{
  "id": "cantillon-capital-management-llp",
  "type": [
    "account"
  ],
  "bankType": [
    "retail"
  ],
  "name": "CANTILLON CAPITAL MANAGEMENT LLP",
  "legalName": "CANTILLON CAPITAL MANAGEMENT LLP",
  "bic": "CCGPGB21XXX",
  "verified": false,
  "status": "live",
  "icon": "https://icons.duckduckgo.com/ip3/www.cantilloncapitalmanagementllp.com.ico",
  "websiteUrl": null,
  "countryHQ": "GB",
  "countries": [
    "GB"
  ],
  "webApplication": true,
  "mobileApps": [],
  "compliance": [],
  "developerPortalUrl": null,
  "apiStandards": [],
  "apiProducts": [],
  "apiAggregators": [],
  "ownership": [],
  "stateOwned": false,
  "stockSymbol": null
}
