{
  "id": "champeil-jean-louis",
  "type": [
    "account"
  ],
  "bankType": [
    "retail"
  ],
  "name": "CHAMPEIL (JEAN-LOUIS)",
  "legalName": "CHAMPEIL (JEAN-LOUIS)",
  "bic": "CHJLFR21XXX",
  "verified": false,
  "status": "live",
  "icon": "https://icons.duckduckgo.com/ip3/www.champeiljeanlouis.com.ico",
  "websiteUrl": null,
  "countryHQ": "FR",
  "countries": [
    "FR"
  ],
  "webApplication": true,
  "mobileApps": [],
  "compliance": [],
  "developerPortalUrl": null,
  "apiStandards": [],
  "apiProducts": [],
  "apiAggregators": [],
  "ownership": [],
  "stateOwned": false,
  "stockSymbol": null
}
