{
  "id": "china-everbright-bank-co-ltd-au",
  "type": [
    "account"
  ],
  "bankType": [
    "retail"
  ],
  "name": "CHINA EVERBRIGHT BANK CO., LTD.",
  "legalName": "CHINA EVERBRIGHT BANK CO., LTD.",
  "verified": false,
  "status": "live",
  "icon": "https://icons.duckduckgo.com/ip3/www.china-everbright-bank-co-ltd.com.ico",
  "websiteUrl": null,
  "countryHQ": "AU",
  "countries": [
    "AU"
  ],
  "webApplication": true,
  "mobileApps": [],
  "compliance": [],
  "developerPortalUrl": null,
  "apiStandards": [],
  "apiProducts": [],
  "apiAggregators": [],
  "ownership": [],
  "stateOwned": false,
  "stockSymbol": null,
  "bic": "EVERAU2S"
}
