{
  "id": "citigroup-global-markets-asia-limited",
  "type": [
    "account"
  ],
  "bankType": [
    "retail"
  ],
  "name": "CITIGROUP GLOBAL MARKETS ASIA LIMITED",
  "legalName": "CITIGROUP GLOBAL MARKETS ASIA LIMITED",
  "bic": "SBHKHKHHXXX",
  "verified": false,
  "status": "live",
  "icon": "https://icons.duckduckgo.com/ip3/www.citigroupglobalmarketsasialimited.com.ico",
  "websiteUrl": null,
  "countryHQ": "HK",
  "countries": [
    "HK"
  ],
  "webApplication": true,
  "mobileApps": [],
  "compliance": [],
  "developerPortalUrl": null,
  "apiStandards": [],
  "apiProducts": [],
  "apiAggregators": [],
  "ownership": [],
  "stateOwned": false,
  "stockSymbol": null
}
