{
  "id": "collinsville-building-and-loan-association",
  "type": [
    "account"
  ],
  "bankType": [
    "retail"
  ],
  "name": "Collinsville Building and Loan Association",
  "legalName": "Collinsville Building and Loan Association",
  "verified": false,
  "status": "live",
  "icon": "https://icons.duckduckgo.com/ip3/www.collinsville-building-and-loan-association.com.ico",
  "websiteUrl": "https://www.collinsvillebuildingandloan.com",
  "countryHQ": "US",
  "countries": [
    "US"
  ],
  "webApplication": true,
  "mobileApps": [],
  "compliance": [],
  "developerPortalUrl": null,
  "apiStandards": [],
  "apiProducts": [],
  "apiAggregators": [
    "plaid"
  ],
  "ownership": [],
  "stateOwned": false,
  "stockSymbol": null
}
