{
  "id": "comune-di-pasiano-di-pordenone",
  "type": [
    "account"
  ],
  "bankType": [
    "retail"
  ],
  "name": "COMUNE DI PASIANO DI PORDENONE",
  "legalName": "COMUNE DI PASIANO DI PORDENONE",
  "verified": false,
  "status": "live",
  "icon": "https://icons.duckduckgo.com/ip3/www.comunedipasianodipordenone.com.ico",
  "websiteUrl": null,
  "countryHQ": "IT",
  "countries": [
    "IT"
  ],
  "webApplication": true,
  "mobileApps": [],
  "compliance": [],
  "developerPortalUrl": null,
  "apiStandards": [],
  "apiProducts": [],
  "apiAggregators": [],
  "ownership": [],
  "stateOwned": false,
  "stockSymbol": null,
  "bic": "CPPOIT21XXX"
}
