{
  "id": "comune-di-montorio-al-vomano",
  "type": [
    "account"
  ],
  "bankType": [
    "retail"
  ],
  "name": "COMUNE DI MONTORIO AL VOMANO",
  "legalName": "COMUNE DI MONTORIO AL VOMANO",
  "verified": false,
  "status": "live",
  "icon": "https://icons.duckduckgo.com/ip3/www.comunedimontorioalvomano.com.ico",
  "websiteUrl": null,
  "countryHQ": "IT",
  "countries": [
    "IT"
  ],
  "webApplication": true,
  "mobileApps": [],
  "compliance": [],
  "developerPortalUrl": null,
  "apiStandards": [],
  "apiProducts": [],
  "apiAggregators": [],
  "ownership": [],
  "stateOwned": false,
  "stockSymbol": null,
  "bic": "CNVOIT31XXX"
}
