{
  "id": "delaware-state-police-federal-credit-union-georgetown-de",
  "type": [
    "account"
  ],
  "bankType": [
    "retail"
  ],
  "name": "Delaware State Police Federal Credit Union (Georgetown, DE)",
  "legalName": "Delaware State Police Federal Credit Union (Georgetown, DE)",
  "verified": false,
  "status": "live",
  "icon": "https://icons.duckduckgo.com/ip3/www.delaware-state-police-federal-credit-union-georgetown-de.com.ico",
  "websiteUrl": "https://www.dspfcu.com/",
  "countryHQ": "US",
  "countries": [
    "US"
  ],
  "webApplication": true,
  "mobileApps": [],
  "compliance": [],
  "developerPortalUrl": null,
  "apiStandards": [],
  "apiProducts": [],
  "apiAggregators": [
    "plaid"
  ],
  "ownership": [],
  "stateOwned": false,
  "stockSymbol": null
}
