{
  "id": "depobank-banca-depositaria-italian-spa-ovvero-in-forma-abbreviata-depobank-it",
  "type": [
    "account"
  ],
  "bankType": [
    "retail"
  ],
  "name": "DEPOBANK - BANCA DEPOSITARIA ITALIAN S.P.A. OVVERO, IN FORMA ABBREVIATA DEPOBANK",
  "legalName": "DEPOBANK - BANCA DEPOSITARIA ITALIAN S.P.A. OVVERO, IN FORMA ABBREVIATA DEPOBANK",
  "verified": false,
  "status": "live",
  "icon": "https://icons.duckduckgo.com/ip3/www.depobank-banca-depositaria-italian-spa-ovvero-in-forma-abbreviata-depobank.com.ico",
  "websiteUrl": null,
  "countryHQ": "IT",
  "countries": [
    "IT"
  ],
  "webApplication": true,
  "mobileApps": [],
  "compliance": [],
  "developerPortalUrl": null,
  "apiStandards": [],
  "apiProducts": [],
  "apiAggregators": [],
  "ownership": [],
  "stateOwned": false,
  "stockSymbol": null,
  "bic": "CEIMITM1"
}
