{
  "id": "deutsche-bank-ag-seoul-branch",
  "type": [
    "account"
  ],
  "bankType": [
    "retail"
  ],
  "name": "DEUTSCHE BANK AG, SEOUL BRANCH",
  "legalName": "DEUTSCHE BANK AG, SEOUL BRANCH",
  "bic": "DEUTKRSEXXX",
  "verified": false,
  "status": "live",
  "icon": "https://icons.duckduckgo.com/ip3/www.deutschebankagseoulbranch.com.ico",
  "websiteUrl": null,
  "countryHQ": "KR",
  "countries": [
    "KR"
  ],
  "webApplication": true,
  "mobileApps": [],
  "compliance": [],
  "developerPortalUrl": null,
  "apiStandards": [],
  "apiProducts": [],
  "apiAggregators": [],
  "ownership": [],
  "stateOwned": false,
  "stockSymbol": null
}
