{
  "id": "dongsuh-securities-international",
  "type": [
    "account"
  ],
  "bankType": [
    "retail"
  ],
  "name": "DONGSUH SECURITIES INTERNATIONAL",
  "legalName": "DONGSUH SECURITIES INTERNATIONAL",
  "verified": false,
  "status": "live",
  "icon": "https://icons.duckduckgo.com/ip3/www.dongsuhsecuritiesinternational.com.ico",
  "websiteUrl": null,
  "countryHQ": "US",
  "countries": [
    "US"
  ],
  "webApplication": true,
  "mobileApps": [],
  "compliance": [],
  "developerPortalUrl": null,
  "apiStandards": [],
  "apiProducts": [],
  "apiAggregators": [],
  "ownership": [],
  "stateOwned": false,
  "stockSymbol": null,
  "bic": "SEDOUS31XXX"
}
