{
  "id": "eagle-community-bank",
  "type": [
    "account"
  ],
  "bankType": [
    "retail"
  ],
  "name": "Eagle Community Bank",
  "legalName": "Eagle Community Bank",
  "verified": false,
  "status": "live",
  "icon": "https://icons.duckduckgo.com/ip3/www.eagle-community-bank.com.ico",
  "websiteUrl": "https://www.eaglecommunitybank.com/",
  "countryHQ": "US",
  "countries": [
    "US"
  ],
  "webApplication": true,
  "mobileApps": [],
  "compliance": [],
  "developerPortalUrl": null,
  "apiStandards": [],
  "apiProducts": [],
  "apiAggregators": [
    "plaid"
  ],
  "ownership": [],
  "stateOwned": false,
  "stockSymbol": null
}
