{
  "id": "fareva",
  "type": [
    "account"
  ],
  "bankType": [
    "retail"
  ],
  "name": "FAREVA",
  "legalName": "FAREVA",
  "bic": "FAVALULLXXX",
  "verified": false,
  "status": "live",
  "icon": "https://icons.duckduckgo.com/ip3/www.fareva.com.ico",
  "websiteUrl": null,
  "countryHQ": "LU",
  "countries": [
    "LU"
  ],
  "webApplication": true,
  "mobileApps": [],
  "compliance": [],
  "developerPortalUrl": null,
  "apiStandards": [],
  "apiProducts": [],
  "apiAggregators": [],
  "ownership": [],
  "stateOwned": false,
  "stockSymbol": null
}
