{
  "id": "fcs-trust-corp-ag",
  "type": [
    "account"
  ],
  "bankType": [
    "retail"
  ],
  "name": "FCS TRUST CORP AG",
  "legalName": "FCS TRUST CORP AG",
  "bic": "FCTUCH21XXX",
  "verified": false,
  "status": "live",
  "icon": "https://icons.duckduckgo.com/ip3/www.fcstrustcorpag.com.ico",
  "websiteUrl": null,
  "countryHQ": "CH",
  "countries": [
    "CH"
  ],
  "webApplication": true,
  "mobileApps": [],
  "compliance": [],
  "developerPortalUrl": null,
  "apiStandards": [],
  "apiProducts": [],
  "apiAggregators": [],
  "ownership": [],
  "stateOwned": false,
  "stockSymbol": null
}
