{
  "id": "fx-africa-foreign-exchange-ptyltd",
  "type": [
    "account"
  ],
  "bankType": [
    "retail"
  ],
  "name": "FX AFRICA FOREIGN EXCHANGE (PTY)LTD",
  "legalName": "FX AFRICA FOREIGN EXCHANGE (PTY)LTD",
  "bic": "FXAFZAJ1XXX",
  "verified": false,
  "status": "live",
  "icon": "https://icons.duckduckgo.com/ip3/www.fxafricaforeignexchangeptyltd.com.ico",
  "websiteUrl": null,
  "countryHQ": "ZA",
  "countries": [
    "ZA"
  ],
  "webApplication": true,
  "mobileApps": [],
  "compliance": [],
  "developerPortalUrl": null,
  "apiStandards": [],
  "apiProducts": [],
  "apiAggregators": [],
  "ownership": [],
  "stateOwned": false,
  "stockSymbol": null
}
