{
  "id": "gardner-lewis-asset-managment-inc",
  "type": [
    "account"
  ],
  "bankType": [
    "retail"
  ],
  "name": "GARDNER LEWIS ASSET MANAGMENT INC.",
  "legalName": "GARDNER LEWIS ASSET MANAGMENT INC.",
  "bic": "GLANUS31XXX",
  "verified": false,
  "status": "live",
  "icon": "https://icons.duckduckgo.com/ip3/www.gardnerlewisassetmanagmentinc.com.ico",
  "websiteUrl": null,
  "countryHQ": "US",
  "countries": [
    "US"
  ],
  "webApplication": true,
  "mobileApps": [],
  "compliance": [],
  "developerPortalUrl": null,
  "apiStandards": [],
  "apiProducts": [],
  "apiAggregators": [],
  "ownership": [],
  "stateOwned": false,
  "stockSymbol": null
}
