{
  "id": "gas-natural-sdg-sa",
  "type": [
    "account"
  ],
  "bankType": [
    "retail"
  ],
  "name": "GAS NATURAL SDG S.A.",
  "legalName": "GAS NATURAL SDG S.A.",
  "verified": false,
  "status": "live",
  "icon": "https://icons.duckduckgo.com/ip3/www.gasnaturalsdgsa.com.ico",
  "websiteUrl": null,
  "countryHQ": "ES",
  "countries": [
    "ES"
  ],
  "webApplication": true,
  "mobileApps": [],
  "compliance": [],
  "developerPortalUrl": null,
  "apiStandards": [],
  "apiProducts": [],
  "apiAggregators": [],
  "ownership": [],
  "stateOwned": false,
  "stockSymbol": null,
  "bic": "GANRESBBXXX"
}
