{
  "id": "ge-corporate-banking-europe-s-a-s",
  "type": [
    "account"
  ],
  "bankType": [
    "retail"
  ],
  "name": "GE CORPORATE BANKING EUROPE S A S",
  "legalName": "GE CORPORATE BANKING EUROPE S A S",
  "verified": false,
  "status": "live",
  "icon": "https://icons.duckduckgo.com/ip3/www.gecorporatebankingeuropesas.com.ico",
  "websiteUrl": null,
  "countryHQ": "FR",
  "countries": [
    "FR"
  ],
  "webApplication": true,
  "mobileApps": [],
  "compliance": [],
  "developerPortalUrl": null,
  "apiStandards": [],
  "apiProducts": [],
  "apiAggregators": [],
  "ownership": [],
  "stateOwned": false,
  "stockSymbol": null,
  "bic": "COTUFRP1XXX"
}
