{
  "id": "ge-money-retail-bank-public-company",
  "type": [
    "account"
  ],
  "bankType": [
    "retail"
  ],
  "name": "GE MONEY RETAIL BANK PUBLIC COMPANY",
  "legalName": "GE MONEY RETAIL BANK PUBLIC COMPANY",
  "verified": false,
  "status": "live",
  "icon": "https://icons.duckduckgo.com/ip3/www.gemoneyretailbankpubliccompany.com.ico",
  "websiteUrl": null,
  "countryHQ": "TH",
  "countries": [
    "TH"
  ],
  "webApplication": true,
  "mobileApps": [],
  "compliance": [],
  "developerPortalUrl": null,
  "apiStandards": [],
  "apiProducts": [],
  "apiAggregators": [],
  "ownership": [],
  "stateOwned": false,
  "stockSymbol": null,
  "bic": "MRPCTHB1XXX"
}
