{
  "id": "graaffs-trust-limited",
  "type": [
    "account"
  ],
  "bankType": [
    "retail"
  ],
  "name": "GRAAFFS TRUST LIMITED",
  "legalName": "GRAAFFS TRUST LIMITED",
  "verified": false,
  "status": "live",
  "icon": "https://icons.duckduckgo.com/ip3/www.graaffstrustlimited.com.ico",
  "websiteUrl": null,
  "countryHQ": "ZA",
  "countries": [
    "ZA"
  ],
  "webApplication": true,
  "mobileApps": [],
  "compliance": [],
  "developerPortalUrl": null,
  "apiStandards": [],
  "apiProducts": [],
  "apiAggregators": [],
  "ownership": [],
  "stateOwned": false,
  "stockSymbol": null,
  "bic": "GRTRZAJ1XXX"
}
