{
  "id": "hjartdal-og-gransherad-sparebank-no",
  "type": [
    "account"
  ],
  "bankType": [
    "universal"
  ],
  "name": "Hjartdal og Gransherad Sparebank",
  "legalName": "HJARTDAL OG GRANSHERAD SPAREBANK",
  "verified": false,
  "icon": "https://ucarecdn.com/e30f5aa0-0a65-43cd-8e4a-c26b8ebe0d4f/-/preview/170x170/-/crop/180x180/center/NO937893299.png",
  "websiteUrl": "https://hjartdalbanken.no/",
  "ownership": [],
  "stateOwned": false,
  "countryHQ": "NO",
  "countries": [
    "NO"
  ],
  "compliance": [
    {
      "regulation": "PSD2",
      "status": "ready"
    }
  ],
  "sandbox": {
    "status": "available",
    "sourceUrl": null
  },
  "developerPortalUrl": "https://api-portal.sdc.dk/",
  "apiStandards": [],
  "apiProducts": [
    {
      "label": "Accounts API",
      "type": "accountInformation",
      "categories": [
        "accounts"
      ],
      "description": null,
      "documentationUrl": null,
      "apiReferenceUrl": null,
      "premium": false,
      "stage": "production"
    },
    {
      "label": "Payments API",
      "type": "paymentInitiation",
      "categories": [
        "payments"
      ],
      "description": null,
      "documentationUrl": null,
      "apiReferenceUrl": null,
      "premium": false,
      "stage": "production"
    }
  ],
  "apiAggregators": [
    "enablebanking"
  ],
  "webApplication": true,
  "mobileApps": [],
  "stockSymbol": null
}
