{
  "id": "hsbc-bank-usa-natoronto-branch-ca",
  "type": [
    "account"
  ],
  "bankType": [
    "retail"
  ],
  "name": "HSBC BANK USA, N.A.(TORONTO BRANCH)",
  "legalName": "HSBC BANK USA, N.A.(TORONTO BRANCH)",
  "verified": false,
  "status": "live",
  "icon": "https://icons.duckduckgo.com/ip3/www.hsbc-bank-usa-natoronto-branch.com.ico",
  "websiteUrl": null,
  "countryHQ": "CA",
  "countries": [
    "CA"
  ],
  "webApplication": true,
  "mobileApps": [],
  "compliance": [],
  "developerPortalUrl": null,
  "apiStandards": [],
  "apiProducts": [],
  "apiAggregators": [],
  "ownership": [],
  "stateOwned": false,
  "stockSymbol": null,
  "bic": "HSBCCAT1"
}
