{
  "id": "kleinwort-benson-ltd",
  "type": [
    "account"
  ],
  "bankType": [
    "retail"
  ],
  "name": "KLEINWORT BENSON LTD",
  "legalName": "KLEINWORT BENSON LTD",
  "bic": "KLBCKRS1XXX",
  "verified": false,
  "status": "live",
  "icon": "https://icons.duckduckgo.com/ip3/www.kleinwortbensonltd.com.ico",
  "websiteUrl": null,
  "countryHQ": "KR",
  "countries": [
    "KR"
  ],
  "webApplication": true,
  "mobileApps": [],
  "compliance": [],
  "developerPortalUrl": null,
  "apiStandards": [],
  "apiProducts": [],
  "apiAggregators": [],
  "ownership": [],
  "stateOwned": false,
  "stockSymbol": null
}
