{
  "id": "lidion-bank-plc-mt",
  "type": [
    "account"
  ],
  "bankType": [
    "retail"
  ],
  "name": "LIDION BANK PLC",
  "legalName": "LIDION BANK PLC",
  "verified": false,
  "status": "live",
  "icon": "https://icons.duckduckgo.com/ip3/www.lidion-bank-plc.com.ico",
  "websiteUrl": null,
  "countryHQ": "MT",
  "countries": [
    "MT"
  ],
  "webApplication": true,
  "mobileApps": [],
  "compliance": [],
  "developerPortalUrl": null,
  "apiStandards": [],
  "apiProducts": [],
  "apiAggregators": [],
  "ownership": [],
  "stateOwned": false,
  "stockSymbol": null,
  "bic": "AGRKMTMT"
}
