{
  "id": "marufuku-securities-co",
  "type": [
    "account"
  ],
  "bankType": [
    "retail"
  ],
  "name": "MARUFUKU SECURITIES CO",
  "legalName": "MARUFUKU SECURITIES CO",
  "bic": "MAREJPJ1XXX",
  "verified": false,
  "status": "live",
  "icon": "https://icons.duckduckgo.com/ip3/www.marufukusecuritiesco.com.ico",
  "websiteUrl": null,
  "countryHQ": "JP",
  "countries": [
    "JP"
  ],
  "webApplication": true,
  "mobileApps": [],
  "compliance": [],
  "developerPortalUrl": null,
  "apiStandards": [],
  "apiProducts": [],
  "apiAggregators": [],
  "ownership": [],
  "stateOwned": false,
  "stockSymbol": null
}
