{
  "id": "mkb-investment-fund-management-company-ltd",
  "type": [
    "account"
  ],
  "bankType": [
    "retail"
  ],
  "name": "MKB INVESTMENT FUND MANAGEMENT COMPANY LTD.",
  "legalName": "MKB INVESTMENT FUND MANAGEMENT COMPANY LTD.",
  "bic": "MIFNHUH1XXX",
  "verified": false,
  "status": "live",
  "icon": "https://icons.duckduckgo.com/ip3/www.mkbinvestmentfundmanagementcompanyltd.com.ico",
  "websiteUrl": null,
  "countryHQ": "HU",
  "countries": [
    "HU"
  ],
  "webApplication": true,
  "mobileApps": [],
  "compliance": [],
  "developerPortalUrl": null,
  "apiStandards": [],
  "apiProducts": [],
  "apiAggregators": [],
  "ownership": [],
  "stateOwned": false,
  "stockSymbol": null
}
