{
  "id": "mvsm-bank-a-rural-bank-since-1953-ph",
  "type": [
    "account"
  ],
  "bankType": [
    "retail"
  ],
  "name": "MVSM BANK (A RURAL BANK SINCE 1953)",
  "legalName": "MVSM BANK (A RURAL BANK SINCE 1953)",
  "verified": false,
  "status": "live",
  "icon": "https://icons.duckduckgo.com/ip3/www.mvsm-bank-a-rural-bank-since-1953.com.ico",
  "websiteUrl": null,
  "countryHQ": "PH",
  "countries": [
    "PH"
  ],
  "webApplication": true,
  "mobileApps": [],
  "compliance": [],
  "developerPortalUrl": null,
  "apiStandards": [],
  "apiProducts": [],
  "apiAggregators": [],
  "ownership": [],
  "stateOwned": false,
  "stockSymbol": null,
  "bic": "MVRSPHM2"
}
