{
  "id": "n-m-rothschild-europe-partnership",
  "type": [
    "account"
  ],
  "bankType": [
    "retail"
  ],
  "name": "N M ROTHSCHILD EUROPE PARTNERSHIP",
  "legalName": "N M ROTHSCHILD EUROPE PARTNERSHIP",
  "verified": false,
  "status": "live",
  "icon": "https://icons.duckduckgo.com/ip3/www.nmrothschildeuropepartnership.com.ico",
  "websiteUrl": null,
  "countryHQ": "GB",
  "countries": [
    "GB"
  ],
  "webApplication": true,
  "mobileApps": [],
  "compliance": [],
  "developerPortalUrl": null,
  "apiStandards": [],
  "apiProducts": [],
  "apiAggregators": [],
  "ownership": [],
  "stateOwned": false,
  "stockSymbol": null,
  "bic": "ROEPGB21XXX"
}
