{
  "id": "newcourt-finance-france-snc-sucursal-en-espana",
  "type": [
    "account"
  ],
  "bankType": [
    "retail"
  ],
  "name": "NEWCOURT FINANCE (FRANCE) S.N.C. SUCURSAL EN ESPANA",
  "legalName": "NEWCOURT FINANCE (FRANCE) S.N.C. SUCURSAL EN ESPANA",
  "bic": "NFFSESM1XXX",
  "verified": false,
  "status": "live",
  "icon": "https://icons.duckduckgo.com/ip3/www.newcourtfinancefrancesncsucursalenespana.com.ico",
  "websiteUrl": null,
  "countryHQ": "ES",
  "countries": [
    "ES"
  ],
  "webApplication": true,
  "mobileApps": [],
  "compliance": [],
  "developerPortalUrl": null,
  "apiStandards": [],
  "apiProducts": [],
  "apiAggregators": [],
  "ownership": [],
  "stateOwned": false,
  "stockSymbol": null
}
