{
  "id": "nlb-skladi-upravljanje-premozenja-doo",
  "type": [
    "account"
  ],
  "bankType": [
    "retail"
  ],
  "name": "NLB SKLADI, UPRAVLJANJE PREMOZENJA, D.O.O.",
  "legalName": "NLB SKLADI, UPRAVLJANJE PREMOZENJA, D.O.O.",
  "verified": false,
  "status": "live",
  "icon": "https://icons.duckduckgo.com/ip3/www.nlbskladiupravljanjepremozenjadoo.com.ico",
  "websiteUrl": null,
  "countryHQ": "SI",
  "countries": [
    "SI"
  ],
  "webApplication": true,
  "mobileApps": [],
  "compliance": [],
  "developerPortalUrl": null,
  "apiStandards": [],
  "apiProducts": [],
  "apiAggregators": [],
  "ownership": [],
  "stateOwned": false,
  "stockSymbol": null,
  "bic": "NSUPSI21XXX"
}
