{
  "id": "nosio-spa",
  "type": [
    "account"
  ],
  "bankType": [
    "retail"
  ],
  "name": "NOSIO SPA",
  "legalName": "NOSIO SPA",
  "bic": "NOIOIT21XXX",
  "verified": false,
  "status": "live",
  "icon": "https://icons.duckduckgo.com/ip3/www.nosiospa.com.ico",
  "websiteUrl": null,
  "countryHQ": "IT",
  "countries": [
    "IT"
  ],
  "webApplication": true,
  "mobileApps": [],
  "compliance": [],
  "developerPortalUrl": null,
  "apiStandards": [],
  "apiProducts": [],
  "apiAggregators": [],
  "ownership": [],
  "stateOwned": false,
  "stockSymbol": null
}
