{
  "id": "paa-capital-pty-ltd",
  "type": [
    "account"
  ],
  "bankType": [
    "retail"
  ],
  "name": "PAA CAPITAL PTY LTD",
  "legalName": "PAA CAPITAL PTY LTD",
  "verified": false,
  "status": "live",
  "icon": "https://icons.duckduckgo.com/ip3/www.paacapitalptyltd.com.ico",
  "websiteUrl": null,
  "countryHQ": "BW",
  "countries": [
    "BW"
  ],
  "webApplication": true,
  "mobileApps": [],
  "compliance": [],
  "developerPortalUrl": null,
  "apiStandards": [],
  "apiProducts": [],
  "apiAggregators": [],
  "ownership": [],
  "stateOwned": false,
  "stockSymbol": null,
  "bic": "PCPYBWG1XXX"
}
