{
  "id": "pt-bhakti-investama-tbk",
  "type": [
    "account"
  ],
  "bankType": [
    "retail"
  ],
  "name": "PT BHAKTI INVESTAMA, TBK",
  "legalName": "PT BHAKTI INVESTAMA, TBK",
  "bic": "BHANIDJ1XXX",
  "verified": false,
  "status": "live",
  "icon": "https://icons.duckduckgo.com/ip3/www.ptbhaktiinvestamatbk.com.ico",
  "websiteUrl": null,
  "countryHQ": "ID",
  "countries": [
    "ID"
  ],
  "webApplication": true,
  "mobileApps": [],
  "compliance": [],
  "developerPortalUrl": null,
  "apiStandards": [],
  "apiProducts": [],
  "apiAggregators": [],
  "ownership": [],
  "stateOwned": false,
  "stockSymbol": null
}
