{
  "id": "pyrrho-management-limited",
  "type": [
    "account"
  ],
  "bankType": [
    "retail"
  ],
  "name": "PYRRHO MANAGEMENT LIMITED",
  "legalName": "PYRRHO MANAGEMENT LIMITED",
  "bic": "PYMAVGV1XXX",
  "verified": false,
  "status": "live",
  "icon": "https://icons.duckduckgo.com/ip3/www.pyrrhomanagementlimited.com.ico",
  "websiteUrl": null,
  "countryHQ": "VG",
  "countries": [
    "VG"
  ],
  "webApplication": true,
  "mobileApps": [],
  "compliance": [],
  "developerPortalUrl": null,
  "apiStandards": [],
  "apiProducts": [],
  "apiAggregators": [],
  "ownership": [],
  "stateOwned": false,
  "stockSymbol": null
}
