{
  "id": "raahen-seudun-osuuspankki",
  "type": [
    "account"
  ],
  "bankType": [
    "retail"
  ],
  "name": "RAAHEN SEUDUN OSUUSPANKKI",
  "legalName": "RAAHEN SEUDUN OSUUSPANKKI",
  "bic": "RASUFI21XXX",
  "verified": false,
  "status": "live",
  "icon": "https://icons.duckduckgo.com/ip3/www.raahenseudunosuuspankki.com.ico",
  "websiteUrl": null,
  "countryHQ": "FI",
  "countries": [
    "FI"
  ],
  "webApplication": true,
  "mobileApps": [],
  "compliance": [],
  "developerPortalUrl": null,
  "apiStandards": [],
  "apiProducts": [],
  "apiAggregators": [],
  "ownership": [],
  "stateOwned": false,
  "stockSymbol": null
}
