{
  "id": "republic-bank-grenada-limited",
  "type": [
    "account"
  ],
  "bankType": [
    "retail"
  ],
  "name": "REPUBLIC BANK GRENADA LIMITED",
  "legalName": "REPUBLIC BANK GRENADA LIMITED",
  "bic": "NCBGGDGDXXX",
  "verified": false,
  "status": "live",
  "icon": "https://icons.duckduckgo.com/ip3/www.republicbankgrenadalimited.com.ico",
  "websiteUrl": null,
  "countryHQ": "GD",
  "countries": [
    "GD"
  ],
  "webApplication": true,
  "mobileApps": [],
  "compliance": [],
  "developerPortalUrl": null,
  "apiStandards": [],
  "apiProducts": [],
  "apiAggregators": [],
  "ownership": [],
  "stateOwned": false,
  "stockSymbol": null
}
