{
  "id": "reserve-bank-of-new-zealand-nz-1",
  "type": [
    "account"
  ],
  "bankType": [
    "retail"
  ],
  "name": "RESERVE BANK OF NEW ZEALAND",
  "legalName": "RESERVE BANK OF NEW ZEALAND",
  "verified": false,
  "status": "live",
  "icon": "https://icons.duckduckgo.com/ip3/www.reservebankofnewzealandnz1.com.ico",
  "websiteUrl": null,
  "countryHQ": "NZ",
  "countries": [
    "NZ"
  ],
  "webApplication": true,
  "mobileApps": [],
  "compliance": [],
  "developerPortalUrl": null,
  "apiStandards": [],
  "apiProducts": [],
  "apiAggregators": [],
  "ownership": [],
  "stateOwned": false,
  "stockSymbol": null,
  "bic": "RBNZNZ2WXXX"
}
