{
  "id": "saigon-bank-for-industry-and-trade-the",
  "type": [
    "account"
  ],
  "bankType": [
    "retail"
  ],
  "name": "SAIGON BANK FOR INDUSTRY AND TRADE, THE",
  "legalName": "SAIGON BANK FOR INDUSTRY AND TRADE, THE",
  "bic": "SBITVNVXXXX",
  "verified": false,
  "status": "live",
  "icon": "https://icons.duckduckgo.com/ip3/www.saigonbankforindustryandtradethe.com.ico",
  "websiteUrl": null,
  "countryHQ": "VN",
  "countries": [
    "VN"
  ],
  "webApplication": true,
  "mobileApps": [],
  "compliance": [],
  "developerPortalUrl": null,
  "apiStandards": [],
  "apiProducts": [],
  "apiAggregators": [],
  "ownership": [],
  "stateOwned": false,
  "stockSymbol": null
}
