{
  "id": "schroder-investment-management-australia-limited",
  "type": [
    "account"
  ],
  "bankType": [
    "retail"
  ],
  "name": "SCHRODER INVESTMENT MANAGEMENT AUSTRALIA LIMITED",
  "legalName": "SCHRODER INVESTMENT MANAGEMENT AUSTRALIA LIMITED",
  "verified": false,
  "status": "live",
  "icon": "https://icons.duckduckgo.com/ip3/www.schroderinvestmentmanagementaustralialimited.com.ico",
  "websiteUrl": null,
  "countryHQ": "AU",
  "countries": [
    "AU"
  ],
  "webApplication": true,
  "mobileApps": [],
  "compliance": [],
  "developerPortalUrl": null,
  "apiStandards": [],
  "apiProducts": [],
  "apiAggregators": [],
  "ownership": [],
  "stateOwned": false,
  "stockSymbol": null,
  "bic": "SIMAAU21XXX"
}
