{
  "id": "sparebank-1-gudbrandsdal",
  "type": [
    "account"
  ],
  "bankType": [
    "retail"
  ],
  "name": "SPAREBANK 1 GUDBRANDSDAL",
  "legalName": "SPAREBANK 1 GUDBRANDSDAL",
  "bic": "SGFSNO21XXX",
  "verified": false,
  "status": "live",
  "icon": "https://icons.duckduckgo.com/ip3/www.sparebank1gudbrandsdal.com.ico",
  "websiteUrl": null,
  "countryHQ": "NO",
  "countries": [
    "NO"
  ],
  "webApplication": true,
  "mobileApps": [],
  "compliance": [],
  "developerPortalUrl": null,
  "apiStandards": [],
  "apiProducts": [],
  "apiAggregators": [
    "volt"
  ],
  "ownership": [],
  "stateOwned": false,
  "stockSymbol": null
}
