{
  "id": "sparkasse-niederoesterreich-mitte-west-ag",
  "type": [
    "account"
  ],
  "bankType": [
    "retail"
  ],
  "name": "SPARKASSE NIEDEROESTERREICH MITTE WEST AG",
  "legalName": "SPARKASSE NIEDEROESTERREICH MITTE WEST AG",
  "verified": false,
  "status": "live",
  "icon": "https://icons.duckduckgo.com/ip3/www.sparkasseniederoesterreichmittewestag.com.ico",
  "websiteUrl": null,
  "countryHQ": "AT",
  "countries": [
    "AT"
  ],
  "webApplication": true,
  "mobileApps": [],
  "compliance": [],
  "developerPortalUrl": null,
  "apiStandards": [],
  "apiProducts": [],
  "apiAggregators": [
    "gocardless",
    "lunchflow"
  ],
  "ownership": [],
  "stateOwned": false,
  "stockSymbol": null,
  "bic": "SPSPAT21XXX"
}
