{
  "id": "stichting-pensioenfonds-ahold",
  "type": [
    "account"
  ],
  "bankType": [
    "retail"
  ],
  "name": "STICHTING PENSIOENFONDS AHOLD",
  "legalName": "STICHTING PENSIOENFONDS AHOLD",
  "verified": false,
  "status": "live",
  "icon": "https://icons.duckduckgo.com/ip3/www.stichtingpensioenfondsahold.com.ico",
  "websiteUrl": null,
  "countryHQ": "NL",
  "countries": [
    "NL"
  ],
  "webApplication": true,
  "mobileApps": [],
  "compliance": [],
  "developerPortalUrl": null,
  "apiStandards": [],
  "apiProducts": [],
  "apiAggregators": [],
  "ownership": [],
  "stateOwned": false,
  "stockSymbol": null,
  "bic": "STNHNL21XXX"
}
