{
  "id": "swedish-capital-trust-and-credit-union-ef",
  "type": [
    "account"
  ],
  "bankType": [
    "retail"
  ],
  "name": "SWEDISH CAPITAL TRUST AND CREDIT UNION EF",
  "legalName": "SWEDISH CAPITAL TRUST AND CREDIT UNION EF",
  "verified": false,
  "status": "live",
  "icon": "https://icons.duckduckgo.com/ip3/www.swedishcapitaltrustandcreditunionef.com.ico",
  "websiteUrl": null,
  "countryHQ": "SE",
  "countries": [
    "SE"
  ],
  "webApplication": true,
  "mobileApps": [],
  "compliance": [],
  "developerPortalUrl": null,
  "apiStandards": [],
  "apiProducts": [],
  "apiAggregators": [],
  "ownership": [],
  "stateOwned": false,
  "stockSymbol": null,
  "bic": "SCTRSES1XXX"
}
