{
  "id": "tabra-and-al-nibal-exchange",
  "type": [
    "account"
  ],
  "bankType": [
    "retail"
  ],
  "name": "TABRA AND AL NIBAL EXCHANGE",
  "legalName": "TABRA AND AL NIBAL EXCHANGE",
  "bic": "TBRAAEA1XXX",
  "verified": false,
  "status": "live",
  "icon": "https://icons.duckduckgo.com/ip3/www.tabraandalnibalexchange.com.ico",
  "websiteUrl": null,
  "countryHQ": "AE",
  "countries": [
    "AE"
  ],
  "webApplication": true,
  "mobileApps": [],
  "compliance": [],
  "developerPortalUrl": null,
  "apiStandards": [],
  "apiProducts": [],
  "apiAggregators": [],
  "ownership": [],
  "stateOwned": false,
  "stockSymbol": null
}
