{
  "id": "the-marion-center-bank-personal",
  "type": [
    "account"
  ],
  "bankType": [
    "retail"
  ],
  "name": "The Marion Center Bank - Personal",
  "legalName": "The Marion Center Bank - Personal",
  "verified": false,
  "status": "live",
  "icon": "https://icons.duckduckgo.com/ip3/www.the-marion-center-bank-personal.com.ico",
  "websiteUrl": "http://www.marioncenterbank.com",
  "countryHQ": "US",
  "countries": [
    "US"
  ],
  "webApplication": true,
  "mobileApps": [],
  "compliance": [],
  "developerPortalUrl": null,
  "apiStandards": [],
  "apiProducts": [],
  "apiAggregators": [
    "plaid"
  ],
  "ownership": [],
  "stateOwned": false,
  "stockSymbol": null
}
