{
  "id": "the-miners-national-bank-of-eveleth",
  "type": [
    "account"
  ],
  "bankType": [
    "retail"
  ],
  "name": "The Miners National Bank of Eveleth",
  "legalName": "The Miners National Bank of Eveleth",
  "verified": false,
  "status": "live",
  "icon": "https://icons.duckduckgo.com/ip3/www.the-miners-national-bank-of-eveleth.com.ico",
  "websiteUrl": "https://www.mnbeveleth.com/",
  "countryHQ": "US",
  "countries": [
    "US"
  ],
  "webApplication": true,
  "mobileApps": [],
  "compliance": [],
  "developerPortalUrl": null,
  "apiStandards": [],
  "apiProducts": [],
  "apiAggregators": [
    "plaid"
  ],
  "ownership": [],
  "stateOwned": false,
  "stockSymbol": null
}
