{
  "id": "tsukuba-bankltd",
  "type": [
    "account"
  ],
  "bankType": [
    "retail"
  ],
  "name": "TSUKUBA BANK,LTD.",
  "legalName": "TSUKUBA BANK,LTD.",
  "bic": "KGBKJPJTXXX",
  "verified": false,
  "status": "live",
  "icon": "https://icons.duckduckgo.com/ip3/www.tsukubabankltd.com.ico",
  "websiteUrl": null,
  "countryHQ": "JP",
  "countries": [
    "JP"
  ],
  "webApplication": true,
  "mobileApps": [],
  "compliance": [],
  "developerPortalUrl": null,
  "apiStandards": [],
  "apiProducts": [],
  "apiAggregators": [],
  "ownership": [],
  "stateOwned": false,
  "stockSymbol": null
}
