{
  "id": "ubs-sdic-fund-management-co-ltd",
  "type": [
    "account"
  ],
  "bankType": [
    "retail"
  ],
  "name": "UBS SDIC FUND MANAGEMENT CO., LTD.",
  "legalName": "UBS SDIC FUND MANAGEMENT CO., LTD.",
  "bic": "USFMCNS1XXX",
  "verified": false,
  "status": "live",
  "icon": "https://icons.duckduckgo.com/ip3/www.ubssdicfundmanagementcoltd.com.ico",
  "websiteUrl": null,
  "countryHQ": "CN",
  "countries": [
    "CN"
  ],
  "webApplication": true,
  "mobileApps": [],
  "compliance": [],
  "developerPortalUrl": null,
  "apiStandards": [],
  "apiProducts": [],
  "apiAggregators": [],
  "ownership": [],
  "stateOwned": false,
  "stockSymbol": null
}
