{
  "id": "unicredit-bank-srbija-ad",
  "type": [
    "account"
  ],
  "bankType": [
    "retail"
  ],
  "name": "UNICREDIT BANK SRBIJA A.D.",
  "legalName": "UNICREDIT BANK SRBIJA A.D.",
  "verified": false,
  "status": "live",
  "icon": "https://icons.duckduckgo.com/ip3/www.unicreditbanksrbijaad.com.ico",
  "websiteUrl": null,
  "countryHQ": "RS",
  "countries": [
    "RS"
  ],
  "webApplication": true,
  "mobileApps": [],
  "compliance": [],
  "developerPortalUrl": null,
  "apiStandards": [],
  "apiProducts": [],
  "apiAggregators": [],
  "ownership": [],
  "stateOwned": false,
  "stockSymbol": null,
  "bic": "BACXRSBGXXX"
}
