{
  "id": "union-banka-d-d-sarajevo",
  "type": [
    "account"
  ],
  "bankType": [
    "retail"
  ],
  "name": "Union Banka D.d. Sarajevo",
  "legalName": "UNION BANKA D.D. SARAJEVO",
  "bic": "UBKSBA22XXX",
  "verified": false,
  "status": "live",
  "icon": null,
  "websiteUrl": null,
  "countryHQ": "BA",
  "countries": [
    "BA"
  ],
  "webApplication": true,
  "mobileApps": [],
  "compliance": [],
  "developerPortalUrl": null,
  "apiStandards": [],
  "apiProducts": [],
  "apiAggregators": [],
  "ownership": [],
  "stateOwned": false,
  "stockSymbol": null
}
