{
  "id": "joust",
  "type": [
    "account"
  ],
  "bankType": [
    "challenger"
  ],
  "name": "Joust",
  "description": "Joust, the all-inclusive banking toolkit for entrepreneurs and freelancers. We do banking, payments and invoices so you can do what matters.",
  "legalName": "Joust Labs, Inc.",
  "ipoStatus": "private",
  "verified": false,
  "status": "live",
  "iconUrl": "https://res.cloudinary.com/apideck/image/upload/v1566680565/radar/icons/joust.png",
  "website": "https://joust.com",
  "ownership": [],
  "bankingLicense": "nbkc",
  "stateOwned": false,
  "countryHQ": "US",
  "countries": [
    "US"
  ],
  "compliance": [],
  "developerPortalUrl": null,
  "developerCommunityUrl": null,
  "openBankProjectUrl": null,
  "slackCommunity": false,
  "apiAuth": [],
  "apiProducts": [],
  "apiStandards": [],
  "webApplication": false,
  "mobileApps": [
    {
      "operatingSystem": "ios",
      "storeUrl": "https://apps.apple.com/app/apple-store/id1437218195"
    },
    {
      "operatingSystem": "android",
      "storeUrl": "https://play.google.com/store/apps/details?id=com.joust.joustbank&hl=en_US"
    }
  ],
  "stockSymbol": null,
  "investorRelationsUrl": null,
  "financialReports": [],
  "twitter": "JoustBanking",
  "crunchbase": "joust-labs",
  "bloomberg": null,
  "github": ""
}
